file_parser/__init__.py
cui_file_parser-1.0.dist-info/METADATA
cui_file_parser-1.0.dist-info/WHEEL
cui_file_parser-1.0.dist-info/top_level.txt
cui_file_parser-1.0.dist-info/RECORD
