Metadata-Version: 2.1
Name: cui-file-parser
Version: 1.0
Summary: Parser file.
Home-page: https://github.com/me/myproject
Author: dingyong.cui
Author-email: 18721296190@163.com
License: MIT
Platform: UNKNOWN
Classifier: License :: OSI Approved :: MIT License
Classifier: Programming Language :: Python
Classifier: Programming Language :: Python :: 3
Classifier: Programming Language :: Python :: 3.6
Classifier: Programming Language :: Python :: Implementation :: CPython
Classifier: Programming Language :: Python :: Implementation :: PyPy
Requires-Python: >=3.6.0
